CHANGES.rst
COPYING
LICENSE
MANIFEST.in
README.rst
setup.py
Umbra.egg-info/PKG-INFO
Umbra.egg-info/SOURCES.txt
Umbra.egg-info/dependency_links.txt
Umbra.egg-info/requires.txt
Umbra.egg-info/top_level.txt
bin/Umbra
docs/help/Umbra_Manual.html
docs/help/Umbra_Manual.rst
docs/help/resources/pictures/Umbra_DevelopmentCentricLayout.jpg
docs/sphinx/Makefile
docs/sphinx/build/doctrees/environment.pickle
docs/sphinx/build/doctrees/index.doctree
docs/sphinx/build/doctrees/resources/pages/about.doctree
docs/sphinx/build/doctrees/resources/pages/api.doctree
docs/sphinx/build/doctrees/resources/pages/changes.doctree
docs/sphinx/build/doctrees/resources/pages/installation.doctree
docs/sphinx/build/doctrees/resources/pages/introduction.doctree
docs/sphinx/build/doctrees/resources/pages/usage.doctree
docs/sphinx/build/doctrees/resources/pages/api/umbra.components.addons.projectsExplorer.models.doctree
docs/sphinx/build/doctrees/resources/pages/api/umbra.components.addons.projectsExplorer.projectsExplorer.doctree
docs/sphinx/build/doctrees/resources/pages/api/umbra.components.addons.projectsExplorer.views.doctree
docs/sphinx/build/doctrees/resources/pages/api/umbra.components.addons.tcpClientUi.tcpClientUi.doctree
docs/sphinx/build/doctrees/resources/pages/api/umbra.components.addons.tcpServerUi.tcpServerUi.doctree
docs/sphinx/build/doctrees/resources/pages/api/umbra.components.addons.traceUi.models.doctree
docs/sphinx/build/doctrees/resources/pages/api/umbra.components.addons.traceUi.nodes.doctree
docs/sphinx/build/doctrees/resources/pages/api/umbra.components.addons.traceUi.traceUi.doctree
docs/sphinx/build/doctrees/resources/pages/api/umbra.components.addons.traceUi.views.doctree
docs/sphinx/build/doctrees/resources/pages/api/umbra.components.factory.componentsManagerUi.componentsManagerUi.doctree
docs/sphinx/build/doctrees/resources/pages/api/umbra.components.factory.componentsManagerUi.models.doctree
docs/sphinx/build/doctrees/resources/pages/api/umbra.components.factory.componentsManagerUi.nodes.doctree
docs/sphinx/build/doctrees/resources/pages/api/umbra.components.factory.componentsManagerUi.views.doctree
