Metadata-Version: 1.1
Name: Umbra
Version: 1.0.9
Summary: Umbra is the main package of sIBL_GUI and sIBL_Reporter.
Home-page: https://github.com/KelSolaar/Umbra
Author: Thomas Mansencal
Author-email: thomas.mansencal@gmail.com
License: GPLv3
Platform: UNKNOWN
Classifier: Development Status :: 5 - Production/Stable
Classifier: Environment :: Console
Classifier: Environment :: MacOS X
Classifier: Environment :: Win32 (MS Windows)
Classifier: Environment :: X11 Applications :: Qt
Classifier: Intended Audience :: Developers
Classifier: License :: OSI Approved :: GNU General Public License v3 (GPLv3)
Classifier: Natural Language :: English
Classifier: Operating System :: OS Independent
Classifier: Programming Language :: Python :: 2.7
Classifier: Topic :: Utilities
